{
    "version": 8,
    "name": "Basic",
    "sources": {
        "mapbox": {
            "type": "vector",
            "url": "mapbox://mapbox.mapbox-streets-v6"
        },
        "grid": {
            "type": "vector",
            "url": "mapbox://devseed.7ws9izi8"
        }
    },
    "sprite": "",
    "glyphs": "",
    "layers": [
        {
            "id": "background",
            "type": "background",
            "paint": {
                "background-color": "#799bbb"
            }
        },
        {
            "id": "water",
            "type": "fill",
            "source": "mapbox",
            "source-layer": "water",
            "paint": {
                "fill-color": "#ace"
            }
        },
        {
            "id": "states",
            "type": "line",
            "source": "mapbox",
            "source-layer": "admin",
            "paint": {
                "line-color": "#4a6d8b"
            }
        },
        {
            "id": "pop",
            "interactive": true,
            "type": "line",
            "source": "grid",
            "source-layer": "footprints",
            "paint": {
                "line-color": "#000"
            }
        },
        {
            "id": "pop0",
            "interactive": true,
            "type": "fill",
            "source": "grid",
            "source-layer": "footprints",
            "paint": {
                "fill-color": "#0ff",
                "fill-opacity": 0
            },
            "filter": [
                "all",
                [
                    ">",
                    "footprint_count",
                    0
                ],
                [
                    "<=",
                    "footprint_count",
                    6.25
                ]
            ]
        },
        {
            "id": "pop1",
            "interactive": true,
            "type": "fill",
            "source": "grid",
            "source-layer": "footprints",
            "paint": {
                "fill-color": "#0ff",
                "fill-opacity": 0.0625
            },
            "filter": [
                "all",
                [
                    ">",
                    "footprint_count",
                    6.25
                ],
                [
                    "<=",
                    "footprint_count",
                    12.5
                ]
            ]
        },
        {
            "id": "pop2",
            "interactive": true,
            "type": "fill",
            "source": "grid",
            "source-layer": "footprints",
            "paint": {
                "fill-color": "#0ff",
                "fill-opacity": 0.125
            },
            "filter": [
                "all",
                [
                    ">",
                    "footprint_count",
                    12.5
                ],
                [
                    "<=",
                    "footprint_count",
                    18.75
                ]
            ]
        },
        {
            "id": "pop3",
            "interactive": true,
            "type": "fill",
            "source": "grid",
            "source-layer": "footprints",
            "paint": {
                "fill-color": "#0ff",
                "fill-opacity": 0.1875
            },
            "filter": [
                "all",
                [
                    ">",
                    "footprint_count",
                    18.75
                ],
                [
                    "<=",
                    "footprint_count",
                    25
                ]
            ]
        },
        {
            "id": "pop4",
            "interactive": true,
            "type": "fill",
            "source": "grid",
            "source-layer": "footprints",
            "paint": {
                "fill-color": "#0ff",
                "fill-opacity": 0.25
            },
            "filter": [
                "all",
                [
                    ">",
                    "footprint_count",
                    25
                ],
                [
                    "<=",
                    "footprint_count",
                    31.25
                ]
            ]
        },
        {
            "id": "pop5",
            "interactive": true,
            "type": "fill",
            "source": "grid",
            "source-layer": "footprints",
            "paint": {
                "fill-color": "#0ff",
                "fill-opacity": 0.3125
            },
            "filter": [
                "all",
                [
                    ">",
                    "footprint_count",
                    31.25
                ],
                [
                    "<=",
                    "footprint_count",
                    37.5
                ]
            ]
        },
        {
            "id": "pop6",
            "interactive": true,
            "type": "fill",
            "source": "grid",
            "source-layer": "footprints",
            "paint": {
                "fill-color": "#0ff",
                "fill-opacity": 0.375
            },
            "filter": [
                "all",
                [
                    ">",
                    "footprint_count",
                    37.5
                ],
                [
                    "<=",
                    "footprint_count",
                    43.75
                ]
            ]
        },
        {
            "id": "pop7",
            "interactive": true,
            "type": "fill",
            "source": "grid",
            "source-layer": "footprints",
            "paint": {
                "fill-color": "#0ff",
                "fill-opacity": 0.4375
            },
            "filter": [
                "all",
                [
                    ">",
                    "footprint_count",
                    43.75
                ],
                [
                    "<=",
                    "footprint_count",
                    50
                ]
            ]
        },
        {
            "id": "pop8",
            "interactive": true,
            "type": "fill",
            "source": "grid",
            "source-layer": "footprints",
            "paint": {
                "fill-color": "#0ff",
                "fill-opacity": 0.5
            },
            "filter": [
                "all",
                [
                    ">",
                    "footprint_count",
                    50
                ],
                [
                    "<=",
                    "footprint_count",
                    56.25
                ]
            ]
        },
        {
            "id": "pop9",
            "interactive": true,
            "type": "fill",
            "source": "grid",
            "source-layer": "footprints",
            "paint": {
                "fill-color": "#0ff",
                "fill-opacity": 0.5625
            },
            "filter": [
                "all",
                [
                    ">",
                    "footprint_count",
                    56.25
                ],
                [
                    "<=",
                    "footprint_count",
                    62.5
                ]
            ]
        },
        {
            "id": "pop10",
            "interactive": true,
            "type": "fill",
            "source": "grid",
            "source-layer": "footprints",
            "paint": {
                "fill-color": "#0ff",
                "fill-opacity": 0.625
            },
            "filter": [
                "all",
                [
                    ">",
                    "footprint_count",
                    62.5
                ],
                [
                    "<=",
                    "footprint_count",
                    68.75
                ]
            ]
        },
        {
            "id": "pop11",
            "interactive": true,
            "type": "fill",
            "source": "grid",
            "source-layer": "footprints",
            "paint": {
                "fill-color": "#0ff",
                "fill-opacity": 0.6875
            },
            "filter": [
                "all",
                [
                    ">",
                    "footprint_count",
                    68.75
                ],
                [
                    "<=",
                    "footprint_count",
                    75
                ]
            ]
        },
        {
            "id": "pop12",
            "interactive": true,
            "type": "fill",
            "source": "grid",
            "source-layer": "footprints",
            "paint": {
                "fill-color": "#0ff",
                "fill-opacity": 0.75
            },
            "filter": [
                "all",
                [
                    ">",
                    "footprint_count",
                    75
                ],
                [
                    "<=",
                    "footprint_count",
                    81.25
                ]
            ]
        },
        {
            "id": "pop13",
            "interactive": true,
            "type": "fill",
            "source": "grid",
            "source-layer": "footprints",
            "paint": {
                "fill-color": "#0ff",
                "fill-opacity": 0.8125
            },
            "filter": [
                "all",
                [
                    ">",
                    "footprint_count",
                    81.25
                ],
                [
                    "<=",
                    "footprint_count",
                    87.5
                ]
            ]
        },
        {
            "id": "pop14",
            "interactive": true,
            "type": "fill",
            "source": "grid",
            "source-layer": "footprints",
            "paint": {
                "fill-color": "#0ff",
                "fill-opacity": 0.875
            },
            "filter": [
                "all",
                [
                    ">",
                    "footprint_count",
                    87.5
                ],
                [
                    "<=",
                    "footprint_count",
                    93.75
                ]
            ]
        },
        {
            "id": "pop15",
            "interactive": true,
            "type": "fill",
            "source": "grid",
            "source-layer": "footprints",
            "paint": {
                "fill-color": "#0ff",
                "fill-opacity": 0.9375
            },
            "filter": [
                "all",
                [
                    ">",
                    "footprint_count",
                    93.75
                ],
                [
                    "<=",
                    "footprint_count",
                    100
                ]
            ]
        }
    ]
}